proxifier/__init__.py
proxifier-0.1.dist-info/METADATA
proxifier-0.1.dist-info/WHEEL
proxifier-0.1.dist-info/top_level.txt
proxifier-0.1.dist-info/RECORD
